pl_crossvalidate/__init__.py
pl_crossvalidate/datamodule.py
pl_crossvalidate/ensemble.py
pl_crossvalidate/trainer.py
pl_crossvalidate-0.1.0.dist-info/LICENSE
pl_crossvalidate-0.1.0.dist-info/METADATA
pl_crossvalidate-0.1.0.dist-info/WHEEL
pl_crossvalidate-0.1.0.dist-info/top_level.txt
pl_crossvalidate-0.1.0.dist-info/RECORD
