Metadata-Version: 2.1
Name: pl-crossvalidate
Version: 0.1.0
Summary: Cross validation made easy in Lightning
Author-email: Nicki Skafte Detlefsen <skaftenicki@gmail.com>
License: Apache License
Requires-Python: >=3.10
License-File: LICENSE
Requires-Dist: torch (>=2.0)
Requires-Dist: lightning (>=2.0)
Requires-Dist: scikit-learn (>=1.0)
Provides-Extra: dev
Requires-Dist: black (==23.3.0) ; extra == 'dev'
Requires-Dist: coverage (==7.2.5) ; extra == 'dev'
Requires-Dist: isort (==5.12.0) ; extra == 'dev'
Requires-Dist: mypy (==1.3.0) ; extra == 'dev'
Requires-Dist: pre-commit (==3.3.1) ; extra == 'dev'
Requires-Dist: pytest (==7.3.1) ; extra == 'dev'
Requires-Dist: python-semantic-release (==7.33.4) ; extra == 'dev'
Requires-Dist: ruff (==0.0.267) ; extra == 'dev'
